raytracepy/__init__.py
raytracepy/config.py
raytracepy/core.py
raytracepy/light.py
raytracepy/light_layouts.py
raytracepy/light_plane_funcs.py
raytracepy/plane.py
raytracepy/raytrace.py
raytracepy-0.0.1.dist-info/LICENSE.txt
raytracepy-0.0.1.dist-info/METADATA
raytracepy-0.0.1.dist-info/WHEEL
raytracepy-0.0.1.dist-info/top_level.txt
raytracepy-0.0.1.dist-info/RECORD
