Metadata-Version: 2.1
Name: raytracepy
Version: 0.0.1
Summary: 3D raytracing package for science
Home-page: https://github.com/dylanwal/raytrace
Author: Dylan Walsh
License: BSD
Platform: any
Classifier: License :: OSI Approved :: BSD License
Classifier: Programming Language :: Python :: 3
Classifier: Programming Language :: Python :: 3 :: Only
Classifier: Programming Language :: Python :: 3.10
Requires-Python: >=3.10
License-File: LICENSE.txt
Requires-Dist: numpy (>=1.19.0)
Requires-Dist: numba (>=0.53.1)
Requires-Dist: plotly (>=5.3.1)
Requires-Dist: scipy (>=1.7.1)
Requires-Dist: pandas (>=1.4.1)
Requires-Dist: datashader (>=0.13.0)
